mastoposter/__init__.py
mastoposter/__main__.py
mastoposter/sources.py
mastoposter/types.py
mastoposter/utils.py
mastoposter/filters/__init__.py
mastoposter/filters/base.py
mastoposter/filters/boost.py
mastoposter/filters/combined.py
mastoposter/filters/media.py
mastoposter/filters/mention.py
mastoposter/filters/spoiler.py
mastoposter/filters/text.py
mastoposter/filters/visibility.py
mastoposter/integrations/__init__.py
mastoposter/integrations/base.py
mastoposter/integrations/telegram.py
mastoposter/integrations/discord/__init__.py
mastoposter/integrations/discord/types.py
mastoposter/text/__init__.py
mastoposter/text/__main__.py
mastoposter/text/html.py
mastoposter/text/markdown.py
mastoposter/text/plain.py
mastoposter-0.2.dist-info/entry_points.txt
mastoposter-0.2.dist-info/LICENSE
mastoposter-0.2.dist-info/WHEEL
mastoposter-0.2.dist-info/METADATA
mastoposter-0.2.dist-info/RECORD
