Metadata-Version: 2.1
Name: mastoposter
Version: 0.2
Summary: Configurable reposter from Mastodon-compatible Fediverse servers
Keywords: mastodon,discord,telegram
Author-email: hatkidchan <hatkidchan@gmail.com>
Requires-Python: >=3.8
Classifier: Environment :: No Input/Output (Daemon)
Classifier: Intended Audience :: End Users/Desktop
Classifier: License :: OSI Approved :: GNU General Public License v3 or later (GPLv3+)
Classifier: Topic :: Communications
Classifier: Topic :: Internet :: WWW/HTTP
Requires-Dist: Jinja2
Requires-Dist: beautifulsoup4[lxml]
Requires-Dist: emoji
Requires-Dist: httpx
Requires-Dist: websockets
Requires-Dist: pytest ; extra == "test"
Project-URL: Source, https://github.com/hatkidchan/mastoposter
Provides-Extra: test
